<?xml version="1.0" encoding="utf-8"?>
<spawns>
	<spawn_map map_id="301310000">
	
	<!--
		Author.....: GiGatR00n v4.7.5.x
		v4.7.5.x (‎15/‎3/‎2015)
	-->	
	
		<!--Repelling Flame Cannon -->
		<!--<spawn npc_id="855010" respawn_time="295">
			<spot x="234.4599" y="194.21619" z="79.589996" h="119"/>
			<spot x="294.62436" y="324.11783" z="79.790443" h="119"/>
		</spawn>-->	
		<!--Unstable Ide Energy -->
		<!--<spawn npc_id="855008" respawn_time="295">
			<spot x="239.78659" y="233.32512" z="94.41362" h="0"/>
			<spot x="288.04398" y="283.51678" z="94.41362" h="0"/>
			<spot x="303.85037" y="313.05411" z="86.938484" h="0"/>
			<spot x="262.40237" y="237.31337" z="88.629883" h="0"/>
			<spot x="223.53351" y="206.04878" z="87.175323" h="0"/>
			<spot x="267.08759" y="280.76672" z="87.703285" h="0"/>
		</spawn>-->
		<!--Unstable Ide Energy -->
		<!--<spawn npc_id="855211" respawn_time="295">
			<spot x="234.38148" y="194.13779" z="83.493095" h="119"/>
			<spot x="234.38148" y="194.13779" z="84.457039" h="119"/>
			<spot x="234.38148" y="194.13779" z="82.377731" h="119"/>
			<spot x="294.3988" y="324.03323" z="82.938377" h="119"/>
			<spot x="294.3988" y="324.03323" z="84.05336" h="119"/>
			<spot x="294.3988" y="324.03323" z="85.105293" h="119"/>
		</spawn>-->
		<!--Destroyer Kunax -->
		<!--<spawn npc_id="234190" respawn_time="295">
				<spot x="264.4382" y="258.58527" z="85.81963" h="30"/>
		</spawn>-->
		<!--Sheban Intelligence Unit Ridgeblade -->
		<spawn npc_id="234186" respawn_time="180">
			<spot x="320.25806" y="258.70612" z="85.17249" h="60"/>
			<spot x="203.69226" y="255.72789" z="85.17249" h="0" walker_id="D2146763507"/>
		</spawn>
		<!--Sheban Intelligence Unit Mongrel-->
		<spawn npc_id="234188" respawn_time="180">
			<spot h="75" x="212.7252" y="205.77171" z="79.8842" walker_id="D2146763485"/>
			<spot h="76" x="313.8899" y="311.33994" z="79.86218" walker_id="D2146756655"/>
		</spawn>		
		<!--Sheban Intelligence Unit Hunter -->
		<spawn npc_id="234187" respawn_time="180">
			<spot x="222.82352" y="207.73462" z="83.259178" h="0" walker_id="D2146763492"/>
			<spot x="305.59592" y="312.74222" z="83.259178" h="0" walker_id="D2146756664"/>
		</spawn>
		<!--Sheban Intelligence Unit Stitch -->
		<spawn npc_id="234189" respawn_time="180">
			<spot x="206.96481" y="259.00137" z="85.17249" h="0" walker_id="D2146763592"/>
			<spot x="323.53064" y="261.9796" z="85.17249" h="61"/>
		</spawn>
		<!--Salade (Asmo Quest Qiver) -->
		<spawn npc_id="802384" respawn_time="180">
			<spot x="254.92552" y="179.36908" z="79.77095" h="90"/>
		</spawn>		
		<!--Talle (Elyos Quest Giver) -->
		<spawn npc_id="802383" respawn_time="180">
			<spot x="274.57217" y="338.79578" z="79.783966" h="30"/>
		</spawn>
		<!--Faction Balance NPC -->
		<!--<spawn npc_id="702320" respawn_time="180">
			<spot x="258.40732" y="169.4749" z="80.489204" h="0"/>
		</spawn>-->
		<!--Faction Balance NPC -->
		<!--<spawn npc_id="702321" respawn_time="180">
			<spot x="270.00262" y="347.99957" z="79.44365" h="0"/>
		</spawn>-->
		<!--Danuar Icon Elyos -->
		<spawn npc_id="702300" respawn_time="180">
			<spot x="286.44296" y="338.70126" z="79.80884" h="101"/>
			<spot x="279.94434" y="332.16602" z="79.80882" h="108"/>
			<!-- Two Additional in Start Point -->
			<spot x="277.11942" y="356.00146" z="79.782295" h="75"/>
			<spot x="263.2041" y="340.77942" z="79.78101" h="15"/>
		</spawn>
		<!--Danuar Icon Asmodian -->
		<spawn npc_id="702301" respawn_time="180">
			<spot x="243.03052" y="179.22969" z="79.82412" h="41"/>
			<spot x="249.32625" y="185.85104" z="79.82412" h="48"/>
			<!-- Two Additional in Start Point -->
			<spot x="251.89086" y="161.98594" z="79.82412" h="15"/>
			<spot x="265.80618" y="177.20798" z="79.769554" h="75"/>
		</spawn>
		<!--Enchanted Book -->
		<!--<spawn npc_id="702405" respawn_time="295">
				<spot x="290.67102" y="317.26324" z="80.099998" h="75"/>
				<spot x="232.19067" y="185.85762" z="80.199997" h="75"/>
				<spot x="238.54938" y="200.84813" z="80" h="15"/>
				<spot x="297.08356" y="332.35382" z="80.099998" h="15"/>
		</spawn>-->

		<!--Sheban Elite Marauder -->
		<!--<spawn npc_id="234753" respawn_time="295">
			<spot x="256.33893" y="259.0221" z="85.81963" h="75"/>
			<spot x="278.2619" y="273.78964" z="92.942535" h="15"/>
		</spawn>-->		
		<!--Sheban Elite Stalwart -->
		<!--<spawn npc_id="234751" respawn_time="295">
			<spot x="273.76373" y="258.95422" z="85.81963" h="15"/>
			<spot x="250.63719" y="244.0336" z="92.942505" h="75"/>
		</spawn>-->
		 <!--Sheban Elite Medic -->
		<!--<spawn npc_id="234754" respawn_time="295">
			<spot x="264.97153" y="249.82945" z="85.81963" h="105"/>
		</spawn>-->
		<!--Sheban Elite Sniper -->
		<!--<spawn npc_id="234752" respawn_time="295">
			<spot x="264.9393" y="267.92413" z="85.81963" h="45"/>
		</spawn>-->

		<!--Flame Vent Elyos -->
		<!--<spawn npc_id="802192" respawn_time="295">
			<spot x="199.18739" y="191.76154" z="80.746552" h="15"/>
		</spawn>-->
		<!--Flame Vent Asmodian -->
		<!--<spawn npc_id="802193" respawn_time="295">
			<spot x="329.79938" y="326.1139" z="80.60217" h="75"/>
		</spawn>-->
	</spawn_map>
</spawns>
