<?xml version="1.0" encoding="UTF-8"?>
<spawns>
    <spawn_map map_id="210040000">
		<beritra_spawn id="7">
			<beritra_type bstate="INVASION">
				<!-- WorldRaid_Control_Effect -->
				<spawn npc_id="702529">
					<spot x="383.20038" y="2930.0217" z="101.836" h="103"/>
				</spawn>
				<!-- WorldRaid_Advent_Effect -->
				<spawn npc_id="702549">
					<spot x="383.20038" y="2930.0217" z="101.836" h="103"/>
				</spawn>
				<!-- Warning Area -->
				<spawn npc_id="832819">
					<spot x="383.20038" y="2930.0217" z="101.836" h="103"/>
				</spawn>
				<!-- Elite Benoid I -->
				<spawn npc_id="236739">
					<spot x="383.20038" y="2930.0217" z="101.836" h="103"/>
				</spawn>
			</beritra_type>
			<beritra_type bstate="PEACE">
			    <!-- WorldRaid_SP_Object -->
				<spawn npc_id="702548">
					<spot x="383.20038" y="2930.0217" z="101.836" h="103"/>
				</spawn>
			</beritra_type>
		</beritra_spawn>
		<beritra_spawn id="8">
			<beritra_type bstate="INVASION">
				<!-- WorldRaid_Control_Effect -->
				<spawn npc_id="702530">
					<spot x="1470.0549" y="1891.9877" z="106.22974" h="7"/>
				</spawn>
				<!-- WorldRaid_Advent_Effect -->
				<spawn npc_id="702549">
					<spot x="1470.0549" y="1891.9877" z="106.22974" h="7"/>
				</spawn>
				<!-- Warning Area -->
				<spawn npc_id="832819">
					<spot x="1470.0549" y="1891.9877" z="106.22974" h="7"/>
				</spawn>
				<!-- Elite Magnorion I -->
				<spawn npc_id="236740">
					<spot x="1470.0549" y="1891.9877" z="106.22974" h="7"/>
				</spawn>
			</beritra_type>
			<beritra_type bstate="PEACE">
			    <!-- WorldRaid_SP_Object -->
				<spawn npc_id="702548">
					<spot x="1470.0549" y="1891.9877" z="106.22974" h="7"/>
				</spawn>
			</beritra_type>
		</beritra_spawn>
		<beritra_spawn id="9">
			<beritra_type bstate="INVASION">
				<!-- WorldRaid_Control_Effect -->
				<spawn npc_id="702531">
					<spot x="540.073" y="2109.0107" z="103.375" h="107"/>
				</spawn>
				<!-- WorldRaid_Advent_Effect -->
				<spawn npc_id="702549">
					<spot x="540.073" y="2109.0107" z="103.375" h="107"/>
				</spawn>
				<!-- Warning Area -->
				<spawn npc_id="832819">
					<spot x="540.073" y="2109.0107" z="103.375" h="107"/>
				</spawn>
				<!-- Elite Eiter I -->
				<spawn npc_id="236741">
					<spot x="540.073" y="2109.0107" z="103.375" h="107"/>
				</spawn>
			</beritra_type>
			<beritra_type bstate="PEACE">
			    <!-- WorldRaid_SP_Object -->
				<spawn npc_id="702548">
					<spot x="540.073" y="2109.0107" z="103.375" h="107"/>
				</spawn>
			</beritra_type>
		</beritra_spawn>
    </spawn_map>
</spawns>